{
  "NewData": {
    "ABSActive": 0,
    "ABSLevel": 0,
    "AirTemperature": 13.094789792603422,
    "AllTimeBest": "00:00:00",
    "BestLapTime": "00:00:00",
    "Brake": 0.0,
    "BrakeBias": 64.0,
    "BrakesTemperatureAvg": 0.0,
    "BrakesTemperatureMax": 0.0,
    "BrakesTemperatureMin": 0.0,
    "BrakeTemperatureFrontLeft": 427.30527678002807,
    "BrakeTemperatureFrontRight": 427.86314787890319,
    "BrakeTemperatureRearLeft": 273.49017020344593,
    "BrakeTemperatureRearRight": 275.4628166429585,
    "CarCoordinates": [
      125.78335571289063,
      5.93904447555542,
      392.36297607421875
    ],
    "Rotation": 0.0,
    "CarDamage1": 0.0,
    "CarDamage2": 0.0,
    "CarDamage3": 0.0,
    "CarDamage4": 0.0,
    "CarDamage5": 0.0,
    "CarDamagesAvg": 0.0,
    "CarDamagesMax": 0.0,
    "CarDamagesMin": 0.0,
    "CarModel": "16WEC Aston Martin Racing",
    "Clutch": 0.0,
    "CompletedLaps": 0,
    "CurrentLap": 1,
    "CurrentLapTime": "00:07:49.9140697",
    "CurrentSectorIndex": 3,
    "DeltaToAllTimeBest": null,
    "DeltaToSessionBest": null,
    "DRSAvailable": 1,
    "DRSEnabled": 0,
    "EngineTorque": -0.06800998247751977,
    "FilteredRpms": 2124.0645406449094,
    "FilteredSpeedKmh": 13.38,
    "FilteredSpeedLocal": 13.38,
    "FilteredSpeedMph": 8.31,
    "Flag_Black": 0,
    "Flag_Blue": 0,
    "Flag_Checkered": 0,
    "Flag_Name": "",
    "Flag_White": 0,
    "Flag_Yellow": 0,
    "Fuel": 58.090785980224609,
    "Throttle": 0.0,
    "Gear": "R",
    "IsInPit": 0,
    "IsInPitLane": 0,
    "LastLapTime": "00:00:00",
    "LastSectorTime": "00:00:00",
    "MapAllowed": true,
    "MaxEngineTorque": 574.50815449082074,
    "MaxFuel": 100.0,
    "MaxRpm": 7300.0,
    "MaxTurbo": 0.0,
    "OilPressure": 0.0,
    "OilTemperature": 67.7625373470882,
    "Opponents": [
      {
        "Name": "Johannes van Overbeek",
        "Position": 1,
        "PositionInClass": 1,
        "Coordinates": [
          -396.12063598632812,
          33.454418182373047,
          842.168701171875
        ],
        "CarName": "16WEC Extreme Speed Motorsports",
        "IsPlayer": false,
        "BestLapTime": "00:01:56.6210000",
        "LastLapTime": "00:01:56.7910000",
        "DeltaToBest": 0.0,
        "DeltaToPlayer": null,
        "CarClass": "ES_P2",
        "IsCarInPit": false,
        "IsCarInPitLane": false,
        "Initials": "JVO",
        "IRacing_IRating": null,
        "CurrentLap": 4,
        "TrackPositionPercent": 0.2006983978994431,
        "TrackPositionPercentToPlayer": 0.290578,
        "CarNumber": "30",
        "CurrentLapHighPrecision": 3.2006983978994432,
        "GaptoLeader": 0.0,
        "GaptoClassLeader": null,
        "GaptoLeaderSimHub": 0.0,
        "LapsToLeader": 0,
        "LapsToClassLeader": -2,
        "LapsToPlayer": 2,
        "GaptoPlayer": null,
        "BestLapSector1": 42.966,
        "BestLapSector2": 39.886,
        "BestLapSector3": 33.769,
        "BestLapSector1Cumulated": 42.966,
        "BestLapSector2Cumulated": 82.852,
        "BestLapSector3Cumulated": 116.621,
        "LastLapSector1": 43.278,
        "LastLapSector2": 39.9,
        "LastLapSector3": 33.613,
        "BestSector1": 43.278,
        "BestSector2": 39.9,
        "BestSector3": 33.613,
        "Speed": 69.621841123239335,
        "RelativeGapToPlayer": -33.887,
        "RelativeDistanceToPlayer": -1812.17
      },
      {
        "Name": "Danny Watts",
        "Position": 2,
        "PositionInClass": 2,
        "Coordinates": [
          119.961669921875,
          -8.31851863861084,
          -29.012519836425781
        ],
        "CarName": "16WEC Strakka Racing",
        "IsPlayer": false,
        "BestLapTime": "00:01:56.7950000",
        "LastLapTime": "00:01:56.7950000",
        "DeltaToBest": 0.174,
        "DeltaToPlayer": null,
        "CarClass": "ES_P2",
        "IsCarInPit": false,
        "IsCarInPitLane": false,
        "Initials": "DWA",
        "IRacing_IRating": null,
        "CurrentLap": 3,
        "TrackPositionPercent": 0.978130995428207,
        "TrackPositionPercentToPlayer": 0.06801,
        "CarNumber": "42",
        "CurrentLapHighPrecision": 2.9781309954282071,
        "GaptoLeader": 27.742752075195312,
        "GaptoClassLeader": null,
        "GaptoLeaderSimHub": 25.95603304359804,
        "LapsToLeader": 0,
        "LapsToClassLeader": -2,
        "LapsToPlayer": 2,
        "GaptoPlayer": null,
        "BestLapSector1": 42.533,
        "BestLapSector2": 40.325,
        "BestLapSector3": 33.937,
        "BestLapSector1Cumulated": 42.533,
        "BestLapSector2Cumulated": 82.858,
        "BestLapSector3Cumulated": 116.795,
        "LastLapSector1": 42.945,
        "LastLapSector2": 39.914,
        "LastLapSector3": 33.937,
        "BestSector1": 42.945,
        "BestSector2": 39.914,
        "BestSector3": 33.937,
        "Speed": 28.846944989626952,
        "RelativeGapToPlayer": -7.931,
        "RelativeDistanceToPlayer": -424.14
      },
      {
        "Name": "David Heinemeier Hansson",
        "Position": 3,
        "PositionInClass": 1,
        "Coordinates": [
          130.31462097167969,
          -3.7790920734405518,
          110.21243286132813
        ],
        "CarName": "16WEC Proton Competition",
        "IsPlayer": false,
        "BestLapTime": "00:00:00",
        "LastLapTime": "00:00:00",
        "DeltaToBest": null,
        "DeltaToPlayer": null,
        "CarClass": "ES_GTE",
        "IsCarInPit": false,
        "IsCarInPitLane": false,
        "Initials": "DHH",
        "IRacing_IRating": null,
        "CurrentLap": 1,
        "TrackPositionPercent": 0.95538986451232644,
        "TrackPositionPercentToPlayer": 0.045269,
        "CarNumber": "88",
        "CurrentLapHighPrecision": 0.95538986451232644,
        "GaptoLeader": null,
        "GaptoClassLeader": null,
        "GaptoLeaderSimHub": 261.850126472139,
        "LapsToLeader": 2,
        "LapsToClassLeader": 0,
        "LapsToPlayer": 0,
        "GaptoPlayer": null,
        "BestLapSector1": null,
        "BestLapSector2": null,
        "BestLapSector3": null,
        "BestLapSector1Cumulated": null,
        "BestLapSector2Cumulated": null,
        "BestLapSector3Cumulated": null,
        "LastLapSector1": null,
        "LastLapSector2": null,
        "LastLapSector3": null,
        "BestSector1": null,
        "BestSector2": null,
        "BestSector3": null,
        "Speed": 59.037614916867078,
        "RelativeGapToPlayer": -5.279,
        "RelativeDistanceToPlayer": -282.32
      },
      {
        "Name": "Filipe Albuquerque",
        "Position": 4,
        "PositionInClass": 3,
        "Coordinates": [
          -380.74606323242188,
          145.37580871582031,
          1884.4229736328125
        ],
        "CarName": "16WEC RGR SPort by Morand",
        "IsPlayer": false,
        "BestLapTime": "00:00:00",
        "LastLapTime": "00:00:00",
        "DeltaToBest": null,
        "DeltaToPlayer": null,
        "CarClass": "ES_P2",
        "IsCarInPit": false,
        "IsCarInPitLane": false,
        "Initials": "FAL",
        "IRacing_IRating": null,
        "CurrentLap": 1,
        "TrackPositionPercent": 0.5448031714425482,
        "TrackPositionPercentToPlayer": -0.365317,
        "CarNumber": "43",
        "CurrentLapHighPrecision": 0.5448031714425482,
        "GaptoLeader": null,
        "GaptoClassLeader": null,
        "GaptoLeaderSimHub": 309.73315720462955,
        "LapsToLeader": 2,
        "LapsToClassLeader": 0,
        "LapsToPlayer": 0,
        "GaptoPlayer": null,
        "BestLapSector1": null,
        "BestLapSector2": null,
        "BestLapSector3": null,
        "BestLapSector1Cumulated": null,
        "BestLapSector2Cumulated": null,
        "BestLapSector3Cumulated": null,
        "LastLapSector1": null,
        "LastLapSector2": null,
        "LastLapSector3": null,
        "BestSector1": null,
        "BestSector2": null,
        "BestSector3": null,
        "Speed": 45.23464215331299,
        "RelativeGapToPlayer": 42.604,
        "RelativeDistanceToPlayer": 2278.28
      },
      {
        "Name": "Pieter-Jan Claeysens",
        "Position": 5,
        "PositionInClass": 2,
        "Coordinates": [
          125.42686462402344,
          5.9538974761962891,
          392.47604370117188
        ],
        "CarName": "16WEC Aston Martin Racing",
        "IsPlayer": true,
        "BestLapTime": "00:00:00",
        "LastLapTime": "00:00:00",
        "DeltaToBest": null,
        "DeltaToPlayer": null,
        "CarClass": "ES_GTE",
        "IsCarInPit": false,
        "IsCarInPitLane": false,
        "Initials": "PCL",
        "IRacing_IRating": null,
        "CurrentLap": 1,
        "TrackPositionPercent": 0.91012064296984274,
        "TrackPositionPercentToPlayer": null,
        "CarNumber": "98",
        "CurrentLapHighPrecision": 0.91012064296984274,
        "GaptoLeader": null,
        "GaptoClassLeader": null,
        "GaptoLeaderSimHub": 267.12946835764495,
        "LapsToLeader": 2,
        "LapsToClassLeader": 0,
        "LapsToPlayer": 0,
        "GaptoPlayer": null,
        "BestLapSector1": null,
        "BestLapSector2": null,
        "BestLapSector3": null,
        "BestLapSector1Cumulated": null,
        "BestLapSector2Cumulated": null,
        "BestLapSector3Cumulated": null,
        "LastLapSector1": null,
        "LastLapSector2": null,
        "LastLapSector3": null,
        "BestSector1": null,
        "BestSector2": null,
        "BestSector3": null,
        "Speed": 3.790111016702046,
        "RelativeGapToPlayer": null,
        "RelativeDistanceToPlayer": null
      }
    ],
    "PitLimiterOn": 0,
    "Position": 5,
    "RemainingLaps": 0,
    "ReplayMode": "Live",
    "RoadTemperature": 13.094789792603422,
    "Rpms": 2124.0645406449094,
    "SessionTimeLeft": "03:52:40.0980000",
    "SessionTypeName": "Practice",
    "SpeedKmh": 13.38,
    "SpeedLocal": 13.38,
    "SpeedLocalUnit": "KMH",
    "SpeedMph": 8.31,
    "TCActive": 0,
    "TCLevel": 3,
    "TotalLaps": 0,
    "TrackCode": "Bathurst",
    "TrackConfig": null,
    "TrackName": "Bathurst",
    "Turbo": 0.0,
    "TurboPercent": 0.0,
    "TyrePressureFrontLeft": 194.78934456042728,
    "TyrePressureFrontRight": 196.71343492349041,
    "TyrePressureRearLeft": 184.46263055208001,
    "TyrePressureRearRight": 184.94999827419176,
    "TyreDirtFrontLeft": 0.0,
    "TyreDirtFrontRight": 0.0,
    "TyreDirtRearLeft": 0.0,
    "TyreDirtRearRight": 0.0,
    "TyresDirtyLevelAvg": 0.0,
    "TyresDirtyLevelMax": 0.0,
    "TyresDirtyLevelMin": 0.0,
    "TyresTemperatureAvg": 85.08049313571388,
    "TyresTemperatureMax": 117.89541823182026,
    "TyresTemperatureMin": 47.831429902910486,
    "TyresWearAvg": 94.298884272575378,
    "TyresWearMax": 97.914755344390869,
    "TyresWearMin": 91.741842031478882,
    "TyreTemperatureFrontLeft": 47.831429902910486,
    "TyreTemperatureFrontRight": 70.967597670419082,
    "TyreTemperatureRearLeft": 117.89541823182026,
    "TyreTemperatureRearRight": 103.62752673770569,
    "TyreTemperatureFrontLeftInner": 59.581653088441954,
    "TyreTemperatureFrontLeftMiddle": 47.792515787769617,
    "TyreTemperatureFrontLeftOuter": 36.120120832519831,
    "TyreTemperatureFrontRightInner": 79.721783532731138,
    "TyreTemperatureFrontRightMiddle": 73.26865239716318,
    "TyreTemperatureFrontRightOuter": 59.91235708136287,
    "TyreTemperatureRearLeftInner": 167.19320248414363,
    "TyreTemperatureRearLeftMiddle": 123.31260557822498,
    "TyreTemperatureRearLeftOuter": 63.180446633092345,
    "TyreTemperatureRearRightInner": 131.1340144804131,
    "TyreTemperatureRearRightMiddle": 103.60012592699297,
    "TyreTemperatureRearRightOuter": 76.148439805711,
    "TyreWearFrontLeft": 93.950057029724121,
    "TyreWearFrontRight": 91.741842031478882,
    "TyreWearRearLeft": 97.914755344390869,
    "TyreWearRearRight": 93.588882684707642,
    "WaterTemperature": 62.851578392782017,
    "TyrePressureUnit": "Kpa",
    "Sector1Time": null,
    "Sector2Time": null,
    "Sector1LastLapTime": null,
    "Sector2LastLapTime": null,
    "Sector3LastLapTime": null,
    "Sector1BestLapTime": null,
    "Sector2BestLapTime": null,
    "Sector3BestLapTime": null,
    "Sector1BestTime": null,
    "Sector2BestTime": null,
    "Sector3BestTime": null,
    "OpponentsCount": 5,
    "CarSettings_MaxRPM": 7300.0,
    "CarSettings_MaxFUEL": 100.0,
    "CarSettings_RedLineRPM": 6205.0,
    "CarSettings_MinimumShownRPM": 0.0,
    "CarSettings_CurrentDisplayedRPMPercent": 29.096774529382319,
    "CarSettings_RPMRedLineReached": 0.0,
    "CarSettings_RedLineDisplayedPercent": 85.0,
    "CarSettings_RPMShiftLight1": 0.0,
    "CarSettings_RPMShiftLight2": 0.0,
    "CarSettings_RPMRedLineSetting": 85.0,
    "PacketTime": "2018-06-21T16:59:45.239352+02:00",
    "MaxSpeedKmh": 271.88,
    "MaxSpeedMph": 168.94,
    "MaxSpeedLocal": 271.88,
    "CarClass": "ES_GTE",
    "SelfsplitDelta": null,
    "BestSplitDelta": null,
    "BestLapOpponent": {
      "Name": "Johannes van Overbeek",
      "Position": 1,
      "PositionInClass": 1,
      "Coordinates": [
        -396.12063598632812,
        33.454418182373047,
        842.168701171875
      ],
      "CarName": "16WEC Extreme Speed Motorsports",
      "IsPlayer": false,
      "BestLapTime": "00:01:56.6210000",
      "LastLapTime": "00:01:56.7910000",
      "DeltaToBest": 0.0,
      "DeltaToPlayer": null,
      "CarClass": "ES_P2",
      "IsCarInPit": false,
      "IsCarInPitLane": false,
      "Initials": "JVO",
      "IRacing_IRating": null,
      "CurrentLap": 4,
      "TrackPositionPercent": 0.2006983978994431,
      "TrackPositionPercentToPlayer": 0.290578,
      "CarNumber": "30",
      "CurrentLapHighPrecision": 3.2006983978994432,
      "GaptoLeader": 0.0,
      "GaptoClassLeader": null,
      "GaptoLeaderSimHub": 0.0,
      "LapsToLeader": 0,
      "LapsToClassLeader": -2,
      "LapsToPlayer": 2,
      "GaptoPlayer": null,
      "BestLapSector1": 42.966,
      "BestLapSector2": 39.886,
      "BestLapSector3": 33.769,
      "BestLapSector1Cumulated": 42.966,
      "BestLapSector2Cumulated": 82.852,
      "BestLapSector3Cumulated": 116.621,
      "LastLapSector1": 43.278,
      "LastLapSector2": 39.9,
      "LastLapSector3": 33.613,
      "BestSector1": 43.278,
      "BestSector2": 39.9,
      "BestSector3": 33.613,
      "Speed": 69.621841123239335,
      "RelativeGapToPlayer": -33.887,
      "RelativeDistanceToPlayer": -1812.17
    },
    "TrackLength": 6236.44140625,
    "FuelUnit": "Liters"
  },
  "GameRunning": true,
  "GamePath": null,
  "GamePaused": false,
  "GameName": "RFactor2"
}