{
  "NewData": {
    "ABSActive": 0,
    "ABSLevel": 0,
    "AirTemperature": 13.095060569484701,
    "AllTimeBest": "00:00:00",
    "BestLapTime": "00:00:00",
    "Brake": 0.0,
    "BrakeBias": 64.0,
    "BrakesTemperatureAvg": 0.0,
    "BrakesTemperatureMax": 0.0,
    "BrakesTemperatureMin": 0.0,
    "BrakeTemperatureFrontLeft": 414.44931304831914,
    "BrakeTemperatureFrontRight": 414.989863070621,
    "BrakeTemperatureRearLeft": 265.40993915354579,
    "BrakeTemperatureRearRight": 267.32133782435369,
    "CarCoordinates": [
      131.23629760742188,
      5.79606294631958,
      392.96450805664062
    ],
    "Rotation": 0.0,
    "CarDamage1": 0.0,
    "CarDamage2": 0.0,
    "CarDamage3": 0.0,
    "CarDamage4": 0.0,
    "CarDamage5": 0.0,
    "CarDamagesAvg": 0.0,
    "CarDamagesMax": 0.0,
    "CarDamagesMin": 0.0,
    "CarModel": "16WEC Aston Martin Racing",
    "Clutch": 0.0,
    "CompletedLaps": 0,
    "CurrentLap": 1,
    "CurrentLapTime": "00:07:51.5116671",
    "CurrentSectorIndex": 3,
    "DeltaToAllTimeBest": null,
    "DeltaToSessionBest": null,
    "DRSAvailable": 1,
    "DRSEnabled": 0,
    "EngineTorque": -5.7838178690872155E-12,
    "FilteredRpms": 2124.0021764643275,
    "FilteredSpeedKmh": 10.9,
    "FilteredSpeedLocal": 10.9,
    "FilteredSpeedMph": 6.77,
    "Flag_Black": 0,
    "Flag_Blue": 0,
    "Flag_Checkered": 0,
    "Flag_Name": "",
    "Flag_White": 0,
    "Flag_Yellow": 0,
    "Fuel": 58.088066101074219,
    "Throttle": 0.0,
    "Gear": "R",
    "IsInPit": 0,
    "IsInPitLane": 0,
    "LastLapTime": "00:00:00",
    "LastSectorTime": "00:00:00",
    "MapAllowed": true,
    "MaxEngineTorque": 574.50815449082074,
    "MaxFuel": 100.0,
    "MaxRpm": 7300.0,
    "MaxTurbo": 0.0,
    "OilPressure": 0.0,
    "OilTemperature": 67.6585449582621,
    "Opponents": [
      {
        "Name": "Johannes van Overbeek",
        "Position": 1,
        "PositionInClass": 1,
        "Coordinates": [
          -397.29660034179688,
          41.638706207275391,
          953.45477294921875
        ],
        "CarName": "16WEC Extreme Speed Motorsports",
        "IsPlayer": false,
        "BestLapTime": "00:01:56.6210000",
        "LastLapTime": "00:01:56.7910000",
        "DeltaToBest": 0.0,
        "DeltaToPlayer": null,
        "CarClass": "ES_P2",
        "IsCarInPit": false,
        "IsCarInPitLane": false,
        "Initials": "JVO",
        "IRacing_IRating": null,
        "CurrentLap": 4,
        "TrackPositionPercent": 0.21859981090227612,
        "TrackPositionPercentToPlayer": 0.308555,
        "CarNumber": "30",
        "CurrentLapHighPrecision": 3.2185998109022762,
        "GaptoLeader": 0.0,
        "GaptoClassLeader": null,
        "GaptoLeaderSimHub": 0.0,
        "LapsToLeader": 0,
        "LapsToClassLeader": -2,
        "LapsToPlayer": 2,
        "GaptoPlayer": null,
        "BestLapSector1": 42.966,
        "BestLapSector2": 39.886,
        "BestLapSector3": 33.769,
        "BestLapSector1Cumulated": 42.966,
        "BestLapSector2Cumulated": 82.852,
        "BestLapSector3Cumulated": 116.621,
        "LastLapSector1": 43.278,
        "LastLapSector2": 39.9,
        "LastLapSector3": 33.613,
        "BestSector1": 43.278,
        "BestSector2": 39.9,
        "BestSector3": 33.613,
        "Speed": 69.805772591966388,
        "RelativeGapToPlayer": -35.984,
        "RelativeDistanceToPlayer": -1924.29
      },
      {
        "Name": "Danny Watts",
        "Position": 2,
        "PositionInClass": 2,
        "Coordinates": [
          76.214324951171875,
          -7.5150189399719238,
          -48.344085693359375
        ],
        "CarName": "16WEC Strakka Racing",
        "IsPlayer": false,
        "BestLapTime": "00:01:56.7950000",
        "LastLapTime": "00:01:56.7950000",
        "DeltaToBest": 0.174,
        "DeltaToPlayer": null,
        "CarClass": "ES_P2",
        "IsCarInPit": false,
        "IsCarInPitLane": false,
        "Initials": "DWA",
        "IRacing_IRating": null,
        "CurrentLap": 3,
        "TrackPositionPercent": 0.98643862717182085,
        "TrackPositionPercentToPlayer": 0.076394,
        "CarNumber": "42",
        "CurrentLapHighPrecision": 2.9864386271718208,
        "GaptoLeader": 27.682373046875,
        "GaptoClassLeader": null,
        "GaptoLeaderSimHub": 27.074869407829453,
        "LapsToLeader": 0,
        "LapsToClassLeader": -2,
        "LapsToPlayer": 2,
        "GaptoPlayer": null,
        "BestLapSector1": 42.533,
        "BestLapSector2": 40.325,
        "BestLapSector3": 33.937,
        "BestLapSector1Cumulated": 42.533,
        "BestLapSector2Cumulated": 82.858,
        "BestLapSector3Cumulated": 116.795,
        "LastLapSector1": 42.945,
        "LastLapSector2": 39.914,
        "LastLapSector3": 33.937,
        "BestSector1": 42.945,
        "BestSector2": 39.914,
        "BestSector3": 33.937,
        "Speed": 35.628488732641031,
        "RelativeGapToPlayer": -8.909,
        "RelativeDistanceToPlayer": -476.43
      },
      {
        "Name": "David Heinemeier Hansson",
        "Position": 3,
        "PositionInClass": 1,
        "Coordinates": [
          130.33879089355469,
          -6.9090719223022461,
          26.689630508422852
        ],
        "CarName": "16WEC Proton Competition",
        "IsPlayer": false,
        "BestLapTime": "00:00:00",
        "LastLapTime": "00:00:00",
        "DeltaToBest": null,
        "DeltaToPlayer": null,
        "CarClass": "ES_GTE",
        "IsCarInPit": false,
        "IsCarInPitLane": false,
        "Initials": "DHH",
        "IRacing_IRating": null,
        "CurrentLap": 1,
        "TrackPositionPercent": 0.96878705303818469,
        "TrackPositionPercentToPlayer": 0.058743,
        "CarNumber": "88",
        "CurrentLapHighPrecision": 0.96878705303818469,
        "GaptoLeader": null,
        "GaptoClassLeader": null,
        "GaptoLeaderSimHub": 262.37541363486821,
        "LapsToLeader": 2,
        "LapsToClassLeader": 0,
        "LapsToPlayer": 0,
        "GaptoPlayer": null,
        "BestLapSector1": null,
        "BestLapSector2": null,
        "BestLapSector3": null,
        "BestLapSector1Cumulated": null,
        "BestLapSector2Cumulated": null,
        "BestLapSector3Cumulated": null,
        "LastLapSector1": null,
        "LastLapSector2": null,
        "LastLapSector3": null,
        "BestSector1": null,
        "BestSector2": null,
        "BestSector3": null,
        "Speed": 39.949407956055708,
        "RelativeGapToPlayer": -6.851,
        "RelativeDistanceToPlayer": -366.35
      },
      {
        "Name": "Filipe Albuquerque",
        "Position": 4,
        "PositionInClass": 3,
        "Coordinates": [
          -325.75543212890625,
          137.39340209960938,
          1879.4996337890625
        ],
        "CarName": "16WEC RGR SPort by Morand",
        "IsPlayer": false,
        "BestLapTime": "00:00:00",
        "LastLapTime": "00:00:00",
        "DeltaToBest": null,
        "DeltaToPlayer": null,
        "CarClass": "ES_P2",
        "IsCarInPit": false,
        "IsCarInPitLane": false,
        "Initials": "FAL",
        "IRacing_IRating": null,
        "CurrentLap": 1,
        "TrackPositionPercent": 0.55403252931828983,
        "TrackPositionPercentToPlayer": -0.356012,
        "CarNumber": "43",
        "CurrentLapHighPrecision": 0.55403252931828983,
        "GaptoLeader": null,
        "GaptoClassLeader": null,
        "GaptoLeaderSimHub": 310.74450094560609,
        "LapsToLeader": 2,
        "LapsToClassLeader": 0,
        "LapsToPlayer": 0,
        "GaptoPlayer": null,
        "BestLapSector1": null,
        "BestLapSector2": null,
        "BestLapSector3": null,
        "BestLapSector1Cumulated": null,
        "BestLapSector2Cumulated": null,
        "BestLapSector3Cumulated": null,
        "LastLapSector1": null,
        "LastLapSector2": null,
        "LastLapSector3": null,
        "BestSector1": null,
        "BestSector2": null,
        "BestSector3": null,
        "Speed": 30.168025035416022,
        "RelativeGapToPlayer": 41.518,
        "RelativeDistanceToPlayer": 2220.25
      },
      {
        "Name": "Pieter-Jan Claeysens",
        "Position": 5,
        "PositionInClass": 2,
        "Coordinates": [
          130.7962646484375,
          5.8065295219421387,
          392.74774169921875
        ],
        "CarName": "16WEC Aston Martin Racing",
        "IsPlayer": true,
        "BestLapTime": "00:00:00",
        "LastLapTime": "00:00:00",
        "DeltaToBest": null,
        "DeltaToPlayer": null,
        "CarClass": "ES_GTE",
        "IsCarInPit": false,
        "IsCarInPitLane": false,
        "Initials": "PCL",
        "IRacing_IRating": null,
        "CurrentLap": 1,
        "TrackPositionPercent": 0.91004446207992462,
        "TrackPositionPercentToPlayer": null,
        "CarNumber": "98",
        "CurrentLapHighPrecision": 0.91004446207992462,
        "GaptoLeader": null,
        "GaptoClassLeader": null,
        "GaptoLeaderSimHub": 269.22603333501144,
        "LapsToLeader": 2,
        "LapsToClassLeader": 0,
        "LapsToPlayer": 0,
        "GaptoPlayer": null,
        "BestLapSector1": null,
        "BestLapSector2": null,
        "BestLapSector3": null,
        "BestLapSector1Cumulated": null,
        "BestLapSector2Cumulated": null,
        "BestLapSector3Cumulated": null,
        "LastLapSector1": null,
        "LastLapSector2": null,
        "LastLapSector3": null,
        "BestSector1": null,
        "BestSector2": null,
        "BestSector3": null,
        "Speed": 3.1061422406425274,
        "RelativeGapToPlayer": null,
        "RelativeDistanceToPlayer": null
      }
    ],
    "PitLimiterOn": 0,
    "Position": 5,
    "RemainingLaps": 0,
    "ReplayMode": "Live",
    "RoadTemperature": 13.095060569484701,
    "Rpms": 2124.0021764643275,
    "SessionTimeLeft": "03:52:38.4380000",
    "SessionTypeName": "Practice",
    "SpeedKmh": 10.9,
    "SpeedLocal": 10.9,
    "SpeedLocalUnit": "KMH",
    "SpeedMph": 6.77,
    "TCActive": 0,
    "TCLevel": 3,
    "TotalLaps": 0,
    "TrackCode": "Bathurst",
    "TrackConfig": null,
    "TrackName": "Bathurst",
    "Turbo": 0.0,
    "TurboPercent": 0.0,
    "TyrePressureFrontLeft": 194.76417351001743,
    "TyrePressureFrontRight": 196.73887922619875,
    "TyrePressureRearLeft": 184.45282013526827,
    "TyrePressureRearRight": 184.96227710526418,
    "TyreDirtFrontLeft": 0.0,
    "TyreDirtFrontRight": 0.0,
    "TyreDirtRearLeft": 0.0,
    "TyreDirtRearRight": 0.0,
    "TyresDirtyLevelAvg": 0.0,
    "TyresDirtyLevelMax": 0.0,
    "TyresDirtyLevelMin": 0.0,
    "TyresTemperatureAvg": 67.413538852010475,
    "TyresTemperatureMax": 77.0269147935997,
    "TyresTemperatureMin": 46.828148915931877,
    "TyresWearAvg": 94.297505915164948,
    "TyresWearMax": 97.914236783981323,
    "TyresWearMin": 91.7398750782013,
    "TyreTemperatureFrontLeft": 46.828148915931877,
    "TyreTemperatureFrontRight": 69.52785582020573,
    "TyreTemperatureRearLeft": 76.2712358783046,
    "TyreTemperatureRearRight": 77.0269147935997,
    "TyreTemperatureFrontLeftInner": 57.797412913827031,
    "TyreTemperatureFrontLeftMiddle": 46.765048044634852,
    "TyreTemperatureFrontLeftOuter": 35.9219857893338,
    "TyreTemperatureFrontRightInner": 75.91662843492287,
    "TyreTemperatureFrontRightMiddle": 72.2358440191004,
    "TyreTemperatureFrontRightOuter": 60.431095006593807,
    "TyreTemperatureRearLeftInner": 100.70764442878209,
    "TyreTemperatureRearLeftMiddle": 78.407617214919128,
    "TyreTemperatureRearLeftOuter": 49.698445991212566,
    "TyreTemperatureRearRightInner": 88.727070187318361,
    "TyreTemperatureRearRightMiddle": 75.176855827074064,
    "TyreTemperatureRearRightOuter": 67.176818366406735,
    "TyreWearFrontLeft": 93.947213888168335,
    "TyreWearFrontRight": 91.7398750782013,
    "TyreWearRearLeft": 97.914236783981323,
    "TyreWearRearRight": 93.588697910308838,
    "WaterTemperature": 63.595880036462347,
    "TyrePressureUnit": "Kpa",
    "Sector1Time": null,
    "Sector2Time": null,
    "Sector1LastLapTime": null,
    "Sector2LastLapTime": null,
    "Sector3LastLapTime": null,
    "Sector1BestLapTime": null,
    "Sector2BestLapTime": null,
    "Sector3BestLapTime": null,
    "Sector1BestTime": null,
    "Sector2BestTime": null,
    "Sector3BestTime": null,
    "OpponentsCount": 5,
    "CarSettings_MaxRPM": 7300.0,
    "CarSettings_MaxFUEL": 100.0,
    "CarSettings_RedLineRPM": 6205.0,
    "CarSettings_MinimumShownRPM": 0.0,
    "CarSettings_CurrentDisplayedRPMPercent": 29.095920225538734,
    "CarSettings_RPMRedLineReached": 0.0,
    "CarSettings_RedLineDisplayedPercent": 85.0,
    "CarSettings_RPMShiftLight1": 0.0,
    "CarSettings_RPMShiftLight2": 0.0,
    "CarSettings_RPMRedLineSetting": 85.0,
    "PacketTime": "2018-06-21T16:59:46.8822641+02:00",
    "MaxSpeedKmh": 271.88,
    "MaxSpeedMph": 168.94,
    "MaxSpeedLocal": 271.88,
    "CarClass": "ES_GTE",
    "SelfsplitDelta": null,
    "BestSplitDelta": null,
    "BestLapOpponent": {
      "Name": "Johannes van Overbeek",
      "Position": 1,
      "PositionInClass": 1,
      "Coordinates": [
        -397.29660034179688,
        41.638706207275391,
        953.45477294921875
      ],
      "CarName": "16WEC Extreme Speed Motorsports",
      "IsPlayer": false,
      "BestLapTime": "00:01:56.6210000",
      "LastLapTime": "00:01:56.7910000",
      "DeltaToBest": 0.0,
      "DeltaToPlayer": null,
      "CarClass": "ES_P2",
      "IsCarInPit": false,
      "IsCarInPitLane": false,
      "Initials": "JVO",
      "IRacing_IRating": null,
      "CurrentLap": 4,
      "TrackPositionPercent": 0.21859981090227612,
      "TrackPositionPercentToPlayer": 0.308555,
      "CarNumber": "30",
      "CurrentLapHighPrecision": 3.2185998109022762,
      "GaptoLeader": 0.0,
      "GaptoClassLeader": null,
      "GaptoLeaderSimHub": 0.0,
      "LapsToLeader": 0,
      "LapsToClassLeader": -2,
      "LapsToPlayer": 2,
      "GaptoPlayer": null,
      "BestLapSector1": 42.966,
      "BestLapSector2": 39.886,
      "BestLapSector3": 33.769,
      "BestLapSector1Cumulated": 42.966,
      "BestLapSector2Cumulated": 82.852,
      "BestLapSector3Cumulated": 116.621,
      "LastLapSector1": 43.278,
      "LastLapSector2": 39.9,
      "LastLapSector3": 33.613,
      "BestSector1": 43.278,
      "BestSector2": 39.9,
      "BestSector3": 33.613,
      "Speed": 69.805772591966388,
      "RelativeGapToPlayer": -35.984,
      "RelativeDistanceToPlayer": -1924.29
    },
    "TrackLength": 6236.44140625,
    "FuelUnit": "Liters"
  },
  "GameRunning": true,
  "GamePath": null,
  "GamePaused": false,
  "GameName": "RFactor2"
}