{
  "NewData": {
    "ABSActive": 0,
    "ABSLevel": 0,
    "AirTemperature": 13.114194835335468,
    "AllTimeBest": "00:00:00",
    "BestLapTime": "00:00:00",
    "Brake": 0.0,
    "BrakeBias": 64.0,
    "BrakesTemperatureAvg": 0.0,
    "BrakesTemperatureMax": 0.0,
    "BrakesTemperatureMin": 0.0,
    "BrakeTemperatureFrontLeft": 45.321375364043831,
    "BrakeTemperatureFrontRight": 22.769074410633152,
    "BrakeTemperatureRearLeft": 81.110426005842555,
    "BrakeTemperatureRearRight": 62.365309717884884,
    "CarCoordinates": [
      137.79595947265625,
      25.831413269042969,
      1257.1534423828125
    ],
    "Rotation": 0.0,
    "CarDamage1": 0.0,
    "CarDamage2": 0.0,
    "CarDamage3": 0.0,
    "CarDamage4": 0.0,
    "CarDamage5": 0.0,
    "CarDamagesAvg": 0.0,
    "CarDamagesMax": 0.0,
    "CarDamagesMin": 0.0,
    "CarModel": "16WEC Aston Martin Racing",
    "Clutch": 0.0,
    "CompletedLaps": 1,
    "CurrentLap": 2,
    "CurrentLapTime": "00:02:09.1230000",
    "CurrentSectorIndex": 3,
    "DeltaToAllTimeBest": null,
    "DeltaToSessionBest": null,
    "DRSAvailable": 1,
    "DRSEnabled": 0,
    "EngineTorque": 500.50378090449715,
    "FilteredRpms": 6825.9711366027559,
    "FilteredSpeedKmh": 252.21,
    "FilteredSpeedLocal": 252.21,
    "FilteredSpeedMph": 156.72,
    "Flag_Black": 0,
    "Flag_Blue": 0,
    "Flag_Checkered": 0,
    "Flag_Name": "",
    "Flag_White": 0,
    "Flag_Yellow": 0,
    "Fuel": 56.371158599853516,
    "Throttle": 100.0,
    "Gear": "6",
    "IsInPit": 0,
    "IsInPitLane": 0,
    "LastLapTime": "00:00:00",
    "LastSectorTime": "00:01:01.1570000",
    "MapAllowed": true,
    "MaxEngineTorque": 574.86236782716014,
    "MaxFuel": 100.0,
    "MaxRpm": 7300.0,
    "MaxTurbo": 0.0,
    "OilPressure": 0.0,
    "OilTemperature": 70.521138041898553,
    "Opponents": [
      {
        "Name": "Johannes van Overbeek",
        "Position": 1,
        "PositionInClass": 1,
        "Coordinates": [
          -554.6893310546875,
          161.00169372558594,
          1875.7967529296875
        ],
        "CarName": "16WEC Extreme Speed Motorsports",
        "IsPlayer": false,
        "BestLapTime": "00:01:56.6210000",
        "LastLapTime": "00:01:57.0970000",
        "DeltaToBest": 0.0,
        "DeltaToPlayer": null,
        "CarClass": "ES_P2",
        "IsCarInPit": false,
        "IsCarInPitLane": false,
        "Initials": "JVO",
        "IRacing_IRating": null,
        "CurrentLap": 5,
        "TrackPositionPercent": 0.51609796940738317,
        "TrackPositionPercentToPlayer": -0.249027,
        "CarNumber": "30",
        "CurrentLapHighPrecision": 4.5160979694073831,
        "GaptoLeader": 0.0,
        "GaptoClassLeader": null,
        "GaptoLeaderSimHub": 0.0,
        "LapsToLeader": 0,
        "LapsToClassLeader": -2,
        "LapsToPlayer": 2,
        "GaptoPlayer": null,
        "BestLapSector1": 42.966,
        "BestLapSector2": 39.886,
        "BestLapSector3": 33.769,
        "BestLapSector1Cumulated": 42.966,
        "BestLapSector2Cumulated": 82.852,
        "BestLapSector3Cumulated": 116.621,
        "LastLapSector1": 43.742,
        "LastLapSector2": 39.77,
        "LastLapSector3": 33.586,
        "BestSector1": 43.742,
        "BestSector2": 39.77,
        "BestSector3": 33.586,
        "Speed": 69.538831906454249,
        "RelativeGapToPlayer": 29.042,
        "RelativeDistanceToPlayer": 1553.04
      },
      {
        "Name": "Danny Watts",
        "Position": 2,
        "PositionInClass": 2,
        "Coordinates": [
          -245.11749267578125,
          -1.5728615522384644,
          -22.392337799072266
        ],
        "CarName": "16WEC Strakka Racing",
        "IsPlayer": false,
        "BestLapTime": "00:01:56.7950000",
        "LastLapTime": "00:00:00",
        "DeltaToBest": 0.174,
        "DeltaToPlayer": null,
        "CarClass": "ES_P2",
        "IsCarInPit": true,
        "IsCarInPitLane": true,
        "Initials": "DWA",
        "IRacing_IRating": null,
        "CurrentLap": 5,
        "TrackPositionPercent": 0.039226919186873523,
        "TrackPositionPercentToPlayer": 0.274102,
        "CarNumber": "42",
        "CurrentLapHighPrecision": 4.0392269191868735,
        "GaptoLeader": 58.772819519042969,
        "GaptoClassLeader": null,
        "GaptoLeaderSimHub": 55.613178747766085,
        "LapsToLeader": 0,
        "LapsToClassLeader": -1,
        "LapsToPlayer": 2,
        "GaptoPlayer": null,
        "BestLapSector1": 42.533,
        "BestLapSector2": 39.896,
        "BestLapSector3": 34.366,
        "BestLapSector1Cumulated": 42.533,
        "BestLapSector2Cumulated": 82.429,
        "BestLapSector3Cumulated": 116.795,
        "LastLapSector1": 42.587,
        "LastLapSector2": 39.842,
        "LastLapSector3": null,
        "BestSector1": 42.587,
        "BestSector2": 39.842,
        "BestSector3": null,
        "Speed": 0.00013913282238760702,
        "RelativeGapToPlayer": -31.966,
        "RelativeDistanceToPlayer": -1709.42
      },
      {
        "Name": "David Heinemeier Hansson",
        "Position": 3,
        "PositionInClass": 1,
        "Coordinates": [
          -388.16165161132812,
          5.8612198829650879,
          83.1365966796875
        ],
        "CarName": "16WEC Proton Competition",
        "IsPlayer": false,
        "BestLapTime": "00:02:13.2470000",
        "LastLapTime": "00:02:13.2470000",
        "DeltaToBest": 16.625999999999998,
        "DeltaToPlayer": null,
        "CarClass": "ES_GTE",
        "IsCarInPit": false,
        "IsCarInPitLane": false,
        "Initials": "DHH",
        "IRacing_IRating": null,
        "CurrentLap": 3,
        "TrackPositionPercent": 0.078877085657385493,
        "TrackPositionPercentToPlayer": 0.313752,
        "CarNumber": "88",
        "CurrentLapHighPrecision": 2.0788770856573855,
        "GaptoLeader": null,
        "GaptoClassLeader": null,
        "GaptoLeaderSimHub": 284.23113668380847,
        "LapsToLeader": 2,
        "LapsToClassLeader": 0,
        "LapsToPlayer": 0,
        "GaptoPlayer": null,
        "BestLapSector1": 48.828,
        "BestLapSector2": 47.707,
        "BestLapSector3": 36.713,
        "BestLapSector1Cumulated": 48.828,
        "BestLapSector2Cumulated": 96.535,
        "BestLapSector3Cumulated": 133.248,
        "LastLapSector1": 48.828,
        "LastLapSector2": 47.707,
        "LastLapSector3": 36.713,
        "BestSector1": 48.828,
        "BestSector2": 47.707,
        "BestSector3": 36.713,
        "Speed": 41.736084670580908,
        "RelativeGapToPlayer": -36.59,
        "RelativeDistanceToPlayer": -1956.7
      },
      {
        "Name": "Filipe Albuquerque",
        "Position": 4,
        "PositionInClass": 3,
        "Coordinates": [
          173.73243713378906,
          3.2500901222229004,
          637.57275390625
        ],
        "CarName": "16WEC RGR SPort by Morand",
        "IsPlayer": false,
        "BestLapTime": "00:00:00",
        "LastLapTime": "00:00:00",
        "DeltaToBest": null,
        "DeltaToPlayer": null,
        "CarClass": "ES_P2",
        "IsCarInPit": false,
        "IsCarInPitLane": false,
        "Initials": "FAL",
        "IRacing_IRating": null,
        "CurrentLap": 2,
        "TrackPositionPercent": 0.86538390470827653,
        "TrackPositionPercentToPlayer": 0.100259,
        "CarNumber": "43",
        "CurrentLapHighPrecision": 1.8653839047082765,
        "GaptoLeader": null,
        "GaptoClassLeader": null,
        "GaptoLeaderSimHub": 309.1289249392745,
        "LapsToLeader": 2,
        "LapsToClassLeader": 0,
        "LapsToPlayer": 0,
        "GaptoPlayer": null,
        "BestLapSector1": 43.033,
        "BestLapSector2": 39.779,
        "BestLapSector3": null,
        "BestLapSector1Cumulated": null,
        "BestLapSector2Cumulated": null,
        "BestLapSector3Cumulated": null,
        "LastLapSector1": null,
        "LastLapSector2": null,
        "LastLapSector3": null,
        "BestSector1": null,
        "BestSector2": null,
        "BestSector3": null,
        "Speed": 75.777511466154223,
        "RelativeGapToPlayer": -11.692,
        "RelativeDistanceToPlayer": -625.26
      },
      {
        "Name": "Pieter-Jan Claeysens",
        "Position": 5,
        "PositionInClass": 2,
        "Coordinates": [
          137.79595947265625,
          25.831413269042969,
          1257.1534423828125
        ],
        "CarName": "16WEC Aston Martin Racing",
        "IsPlayer": true,
        "BestLapTime": "00:00:00",
        "LastLapTime": "00:00:00",
        "DeltaToBest": null,
        "DeltaToPlayer": null,
        "CarClass": "ES_GTE",
        "IsCarInPit": false,
        "IsCarInPitLane": false,
        "Initials": "PCL",
        "IRacing_IRating": null,
        "CurrentLap": 2,
        "TrackPositionPercent": 0.76512539076960084,
        "TrackPositionPercentToPlayer": null,
        "CarNumber": "98",
        "CurrentLapHighPrecision": 1.765125390769601,
        "GaptoLeader": null,
        "GaptoClassLeader": null,
        "GaptoLeaderSimHub": 320.82117309331682,
        "LapsToLeader": 2,
        "LapsToClassLeader": 0,
        "LapsToPlayer": 0,
        "GaptoPlayer": null,
        "BestLapSector1": 60.045,
        "BestLapSector2": 61.157,
        "BestLapSector3": null,
        "BestLapSector1Cumulated": null,
        "BestLapSector2Cumulated": null,
        "BestLapSector3Cumulated": null,
        "LastLapSector1": null,
        "LastLapSector2": null,
        "LastLapSector3": null,
        "BestSector1": null,
        "BestSector2": null,
        "BestSector3": null,
        "Speed": 70.059159488416185,
        "RelativeGapToPlayer": null,
        "RelativeDistanceToPlayer": null
      }
    ],
    "PitLimiterOn": 0,
    "Position": 5,
    "RemainingLaps": 0,
    "ReplayMode": "Live",
    "RoadTemperature": 13.114194835335468,
    "Rpms": 6825.9711366027559,
    "SessionTimeLeft": "03:50:06.9970000",
    "SessionTypeName": "Practice",
    "SpeedKmh": 252.21,
    "SpeedLocal": 252.21,
    "SpeedLocalUnit": "KMH",
    "SpeedMph": 156.72,
    "TCActive": 0,
    "TCLevel": 3,
    "TotalLaps": 0,
    "TrackCode": "Bathurst",
    "TrackConfig": null,
    "TrackName": "Bathurst",
    "Turbo": 0.0,
    "TurboPercent": 0.0,
    "TyrePressureFrontLeft": 196.89993067684381,
    "TyrePressureFrontRight": 205.63404519928028,
    "TyrePressureRearLeft": 190.40478827790469,
    "TyrePressureRearRight": 190.10963399203959,
    "TyreDirtFrontLeft": 0.0,
    "TyreDirtFrontRight": 0.0,
    "TyreDirtRearLeft": 0.0,
    "TyreDirtRearRight": 0.0,
    "TyresDirtyLevelAvg": 0.0,
    "TyresDirtyLevelMax": 0.0,
    "TyresDirtyLevelMin": 0.0,
    "TyresTemperatureAvg": 63.390272338660438,
    "TyresTemperatureMax": 108.00436539059911,
    "TyresTemperatureMin": 43.459542674135093,
    "TyresWearAvg": 93.287302553653717,
    "TyresWearMax": 96.919572353363037,
    "TyresWearMin": 90.391582250595093,
    "TyreTemperatureFrontLeft": 108.00436539059911,
    "TyreTemperatureFrontRight": 57.561713595419349,
    "TyreTemperatureRearLeft": 43.459542674135093,
    "TyreTemperatureRearRight": 44.535467694488204,
    "TyreTemperatureFrontLeftInner": 129.05688383362246,
    "TyreTemperatureFrontLeftMiddle": 107.99292015689787,
    "TyreTemperatureFrontLeftOuter": 86.963292181276927,
    "TyreTemperatureFrontRightInner": 67.81714002007277,
    "TyreTemperatureFrontRightMiddle": 56.061273093649049,
    "TyreTemperatureFrontRightOuter": 48.806727672536283,
    "TyreTemperatureRearLeftInner": 47.2224044492242,
    "TyreTemperatureRearLeftMiddle": 44.231849669403118,
    "TyreTemperatureRearLeftOuter": 38.924373903777962,
    "TyreTemperatureRearRightInner": 52.466375497755848,
    "TyreTemperatureRearRightMiddle": 41.561788124319719,
    "TyreTemperatureRearRightOuter": 39.5782394613891,
    "TyreWearFrontLeft": 93.661332130432129,
    "TyreWearFrontRight": 90.391582250595093,
    "TyreWearRearLeft": 96.919572353363037,
    "TyreWearRearRight": 92.176723480224609,
    "WaterTemperature": 51.181698492855048,
    "TyrePressureUnit": "Kpa",
    "Sector1Time": "00:01:00.0450000",
    "Sector2Time": "00:01:01.1570000",
    "Sector1LastLapTime": null,
    "Sector2LastLapTime": null,
    "Sector3LastLapTime": null,
    "Sector1BestLapTime": null,
    "Sector2BestLapTime": null,
    "Sector3BestLapTime": null,
    "Sector1BestTime": "00:01:00.0450000",
    "Sector2BestTime": "00:01:01.1570000",
    "Sector3BestTime": null,
    "OpponentsCount": 5,
    "CarSettings_MaxRPM": 7300.0,
    "CarSettings_MaxFUEL": 100.0,
    "CarSettings_RedLineRPM": 6205.0,
    "CarSettings_MinimumShownRPM": 0.0,
    "CarSettings_CurrentDisplayedRPMPercent": 93.506453926065149,
    "CarSettings_RPMRedLineReached": 1.0,
    "CarSettings_RedLineDisplayedPercent": 85.0,
    "CarSettings_RPMShiftLight1": 1.0,
    "CarSettings_RPMShiftLight2": 1.0,
    "CarSettings_RPMRedLineSetting": 85.0,
    "PacketTime": "2018-06-21T17:02:18.3340215+02:00",
    "MaxSpeedKmh": 271.88,
    "MaxSpeedMph": 168.94,
    "MaxSpeedLocal": 271.88,
    "CarClass": "ES_GTE",
    "SelfsplitDelta": null,
    "BestSplitDelta": 38.35,
    "BestLapOpponent": {
      "Name": "Johannes van Overbeek",
      "Position": 1,
      "PositionInClass": 1,
      "Coordinates": [
        -554.6893310546875,
        161.00169372558594,
        1875.7967529296875
      ],
      "CarName": "16WEC Extreme Speed Motorsports",
      "IsPlayer": false,
      "BestLapTime": "00:01:56.6210000",
      "LastLapTime": "00:01:57.0970000",
      "DeltaToBest": 0.0,
      "DeltaToPlayer": null,
      "CarClass": "ES_P2",
      "IsCarInPit": false,
      "IsCarInPitLane": false,
      "Initials": "JVO",
      "IRacing_IRating": null,
      "CurrentLap": 5,
      "TrackPositionPercent": 0.51609796940738317,
      "TrackPositionPercentToPlayer": -0.249027,
      "CarNumber": "30",
      "CurrentLapHighPrecision": 4.5160979694073831,
      "GaptoLeader": 0.0,
      "GaptoClassLeader": null,
      "GaptoLeaderSimHub": 0.0,
      "LapsToLeader": 0,
      "LapsToClassLeader": -2,
      "LapsToPlayer": 2,
      "GaptoPlayer": null,
      "BestLapSector1": 42.966,
      "BestLapSector2": 39.886,
      "BestLapSector3": 33.769,
      "BestLapSector1Cumulated": 42.966,
      "BestLapSector2Cumulated": 82.852,
      "BestLapSector3Cumulated": 116.621,
      "LastLapSector1": 43.742,
      "LastLapSector2": 39.77,
      "LastLapSector3": 33.586,
      "BestSector1": 43.742,
      "BestSector2": 39.77,
      "BestSector3": 33.586,
      "Speed": 69.538831906454249,
      "RelativeGapToPlayer": 29.042,
      "RelativeDistanceToPlayer": 1553.04
    },
    "TrackLength": 6236.44140625,
    "FuelUnit": "Liters"
  },
  "GameRunning": true,
  "GamePath": null,
  "GamePaused": false,
  "GameName": "RFactor2"
}