{
  "NewData": {
    "ABSActive": 0,
    "ABSLevel": 0,
    "AirTemperature": 13.081140685369292,
    "AllTimeBest": "00:00:00",
    "BestLapTime": "00:00:00",
    "Brake": 0.0,
    "BrakeBias": 64.0,
    "BrakesTemperatureAvg": 0.0,
    "BrakesTemperatureMax": 0.0,
    "BrakesTemperatureMin": 0.0,
    "BrakeTemperatureFrontLeft": 161.94181348918932,
    "BrakeTemperatureFrontRight": 203.0949124487945,
    "BrakeTemperatureRearLeft": 155.1485798622748,
    "BrakeTemperatureRearRight": 158.58890363541298,
    "CarCoordinates": [
      -570.43548583984375,
      161.38119506835938,
      1881.83544921875
    ],
    "Rotation": 0.0,
    "CarDamage1": 0.0,
    "CarDamage2": 0.0,
    "CarDamage3": 0.0,
    "CarDamage4": 0.0,
    "CarDamage5": 0.0,
    "CarDamagesAvg": 0.0,
    "CarDamagesMax": 0.0,
    "CarDamagesMin": 0.0,
    "CarModel": "16WEC Aston Martin Racing",
    "Clutch": 0.0,
    "CompletedLaps": 0,
    "CurrentLap": 1,
    "CurrentLapTime": "00:06:43.8000000",
    "CurrentSectorIndex": 2,
    "DeltaToAllTimeBest": null,
    "DeltaToSessionBest": null,
    "DRSAvailable": 1,
    "DRSEnabled": 0,
    "EngineTorque": 526.36972145312257,
    "FilteredRpms": 6363.5424861181518,
    "FilteredSpeedKmh": 173.35,
    "FilteredSpeedLocal": 173.35,
    "FilteredSpeedMph": 107.71,
    "Flag_Black": 0,
    "Flag_Blue": 0,
    "Flag_Checkered": 0,
    "Flag_Name": "",
    "Flag_White": 0,
    "Flag_Yellow": 0,
    "Fuel": 58.879707336425781,
    "Throttle": 100.0,
    "Gear": "4",
    "IsInPit": 0,
    "IsInPitLane": 0,
    "LastLapTime": "00:00:00",
    "LastSectorTime": "00:00:00",
    "MapAllowed": true,
    "MaxEngineTorque": 574.45241271725922,
    "MaxFuel": 100.0,
    "MaxRpm": 7300.0,
    "MaxTurbo": 0.0,
    "OilPressure": 0.0,
    "OilTemperature": 70.297757945085436,
    "Opponents": [
      {
        "Name": "Johannes van Overbeek",
        "Position": 1,
        "PositionInClass": 1,
        "Coordinates": [
          9.7485599517822266,
          88.4277114868164,
          2078.450927734375
        ],
        "CarName": "16WEC Extreme Speed Motorsports",
        "IsPlayer": false,
        "BestLapTime": "00:01:56.6210000",
        "LastLapTime": "00:01:56.6210000",
        "DeltaToBest": 0.0,
        "DeltaToPlayer": null,
        "CarClass": "ES_P2",
        "IsCarInPit": false,
        "IsCarInPitLane": false,
        "Initials": "JVO",
        "IRacing_IRating": null,
        "CurrentLap": 3,
        "TrackPositionPercent": 0.62027862475407591,
        "TrackPositionPercentToPlayer": 0.107128,
        "CarNumber": "30",
        "CurrentLapHighPrecision": 2.6202786247540759,
        "GaptoLeader": 0.0,
        "GaptoClassLeader": null,
        "GaptoLeaderSimHub": 0.0,
        "LapsToLeader": 0,
        "LapsToClassLeader": -2,
        "LapsToPlayer": 2,
        "GaptoPlayer": null,
        "BestLapSector1": 42.966,
        "BestLapSector2": 39.886,
        "BestLapSector3": 33.769,
        "BestLapSector1Cumulated": 42.966,
        "BestLapSector2Cumulated": 82.852,
        "BestLapSector3Cumulated": 116.621,
        "LastLapSector1": 42.966,
        "LastLapSector2": 39.886,
        "LastLapSector3": 33.769,
        "BestSector1": 42.966,
        "BestSector2": 39.886,
        "BestSector3": 33.769,
        "Speed": 28.540252144947452,
        "RelativeGapToPlayer": -12.493,
        "RelativeDistanceToPlayer": -668.1
      },
      {
        "Name": "Danny Watts",
        "Position": 2,
        "PositionInClass": 2,
        "Coordinates": [
          -945.1915283203125,
          162.35345458984375,
          1554.8624267578125
        ],
        "CarName": "16WEC Strakka Racing",
        "IsPlayer": false,
        "BestLapTime": "00:01:56.7950000",
        "LastLapTime": "00:01:56.7950000",
        "DeltaToBest": 0.174,
        "DeltaToPlayer": null,
        "CarClass": "ES_P2",
        "IsCarInPit": false,
        "IsCarInPitLane": false,
        "Initials": "DWA",
        "IRacing_IRating": null,
        "CurrentLap": 3,
        "TrackPositionPercent": 0.414870204362088,
        "TrackPositionPercentToPlayer": -0.09828,
        "CarNumber": "42",
        "CurrentLapHighPrecision": 2.4148702043620878,
        "GaptoLeader": 27.445686340332031,
        "GaptoClassLeader": null,
        "GaptoLeaderSimHub": 23.954935394534061,
        "LapsToLeader": 0,
        "LapsToClassLeader": -1,
        "LapsToPlayer": 1,
        "GaptoPlayer": null,
        "BestLapSector1": 42.533,
        "BestLapSector2": 40.325,
        "BestLapSector3": 33.937,
        "BestLapSector1Cumulated": 42.533,
        "BestLapSector2Cumulated": 82.858,
        "BestLapSector3Cumulated": 116.795,
        "LastLapSector1": 42.945,
        "LastLapSector2": 39.914,
        "LastLapSector3": 33.937,
        "BestSector1": 42.945,
        "BestSector2": 39.914,
        "BestSector3": 33.937,
        "Speed": 62.104955526921394,
        "RelativeGapToPlayer": 11.462,
        "RelativeDistanceToPlayer": 612.92
      },
      {
        "Name": "David Heinemeier Hansson",
        "Position": 3,
        "PositionInClass": 1,
        "Coordinates": [
          -921.17132568359375,
          163.75128173828125,
          1740.9805908203125
        ],
        "CarName": "16WEC Proton Competition",
        "IsPlayer": false,
        "BestLapTime": "00:00:00",
        "LastLapTime": "00:00:00",
        "DeltaToBest": null,
        "DeltaToPlayer": null,
        "CarClass": "ES_GTE",
        "IsCarInPit": false,
        "IsCarInPitLane": false,
        "Initials": "DHH",
        "IRacing_IRating": null,
        "CurrentLap": 1,
        "TrackPositionPercent": 0.44662119353923418,
        "TrackPositionPercentToPlayer": -0.066529,
        "CarNumber": "88",
        "CurrentLapHighPrecision": 0.44662119353923418,
        "GaptoLeader": null,
        "GaptoClassLeader": null,
        "GaptoLeaderSimHub": 253.49410328570605,
        "LapsToLeader": 2,
        "LapsToClassLeader": 0,
        "LapsToPlayer": 0,
        "GaptoPlayer": null,
        "BestLapSector1": null,
        "BestLapSector2": null,
        "BestLapSector3": null,
        "BestLapSector1Cumulated": null,
        "BestLapSector2Cumulated": null,
        "BestLapSector3Cumulated": null,
        "LastLapSector1": null,
        "LastLapSector2": null,
        "LastLapSector3": null,
        "BestSector1": null,
        "BestSector2": null,
        "BestSector3": null,
        "Speed": 49.521111748262427,
        "RelativeGapToPlayer": 7.759,
        "RelativeDistanceToPlayer": 414.9
      },
      {
        "Name": "Filipe Albuquerque",
        "Position": 4,
        "PositionInClass": 3,
        "Coordinates": [
          -298.65835571289062,
          -0.5070720911026001,
          -22.64869499206543
        ],
        "CarName": "16WEC RGR SPort by Morand",
        "IsPlayer": false,
        "BestLapTime": "00:00:00",
        "LastLapTime": "00:00:00",
        "DeltaToBest": null,
        "DeltaToPlayer": null,
        "CarClass": "ES_P2",
        "IsCarInPit": true,
        "IsCarInPitLane": true,
        "Initials": "FAL",
        "IRacing_IRating": null,
        "CurrentLap": 1,
        "TrackPositionPercent": 0.04813120173513917,
        "TrackPositionPercentToPlayer": -0.465019,
        "CarNumber": "43",
        "CurrentLapHighPrecision": 0.04813120173513917,
        "GaptoLeader": null,
        "GaptoClassLeader": null,
        "GaptoLeaderSimHub": 299.96640461989142,
        "LapsToLeader": 2,
        "LapsToClassLeader": 0,
        "LapsToPlayer": 0,
        "GaptoPlayer": null,
        "BestLapSector1": null,
        "BestLapSector2": null,
        "BestLapSector3": null,
        "BestLapSector1Cumulated": null,
        "BestLapSector2Cumulated": null,
        "BestLapSector3Cumulated": null,
        "LastLapSector1": null,
        "LastLapSector2": null,
        "LastLapSector3": null,
        "BestSector1": null,
        "BestSector2": null,
        "BestSector3": null,
        "Speed": 0.0015587685757777379,
        "RelativeGapToPlayer": 54.231,
        "RelativeDistanceToPlayer": 2900.06
      },
      {
        "Name": "Pieter-Jan Claeysens",
        "Position": 5,
        "PositionInClass": 2,
        "Coordinates": [
          -572.32318115234375,
          161.41159057617188,
          1882.2015380859375
        ],
        "CarName": "16WEC Aston Martin Racing",
        "IsPlayer": true,
        "BestLapTime": "00:00:00",
        "LastLapTime": "00:00:00",
        "DeltaToBest": null,
        "DeltaToPlayer": null,
        "CarClass": "ES_GTE",
        "IsCarInPit": false,
        "IsCarInPitLane": false,
        "Initials": "PCL",
        "IRacing_IRating": null,
        "CurrentLap": 1,
        "TrackPositionPercent": 0.51315032486099532,
        "TrackPositionPercentToPlayer": null,
        "CarNumber": "98",
        "CurrentLapHighPrecision": 0.51315032486099532,
        "GaptoLeader": null,
        "GaptoClassLeader": null,
        "GaptoLeaderSimHub": 245.73540946183096,
        "LapsToLeader": 2,
        "LapsToClassLeader": 0,
        "LapsToPlayer": 0,
        "GaptoPlayer": null,
        "BestLapSector1": null,
        "BestLapSector2": null,
        "BestLapSector3": null,
        "BestLapSector1Cumulated": null,
        "BestLapSector2Cumulated": null,
        "BestLapSector3Cumulated": null,
        "LastLapSector1": null,
        "LastLapSector2": null,
        "LastLapSector3": null,
        "BestSector1": null,
        "BestSector2": null,
        "BestSector3": null,
        "Speed": 48.003614169269028,
        "RelativeGapToPlayer": null,
        "RelativeDistanceToPlayer": null
      }
    ],
    "PitLimiterOn": 0,
    "Position": 5,
    "RemainingLaps": 0,
    "ReplayMode": "Live",
    "RoadTemperature": 13.081140685369292,
    "Rpms": 6363.5424861181518,
    "SessionTimeLeft": "03:53:46.1580000",
    "SessionTypeName": "Practice",
    "SpeedKmh": 173.35,
    "SpeedLocal": 173.35,
    "SpeedLocalUnit": "KMH",
    "SpeedMph": 107.71,
    "TCActive": 0,
    "TCLevel": 3,
    "TotalLaps": 0,
    "TrackCode": "Bathurst",
    "TrackConfig": null,
    "TrackName": "Bathurst",
    "Turbo": 0.0,
    "TurboPercent": 0.0,
    "TyrePressureFrontLeft": 188.07223934029628,
    "TyrePressureFrontRight": 189.29812990261385,
    "TyrePressureRearLeft": 180.06495270931509,
    "TyrePressureRearRight": 180.39655283982756,
    "TyreDirtFrontLeft": 0.0,
    "TyreDirtFrontRight": 0.0,
    "TyreDirtRearLeft": 0.0,
    "TyreDirtRearRight": 0.0,
    "TyresDirtyLevelAvg": 0.0,
    "TyresDirtyLevelMax": 0.0,
    "TyresDirtyLevelMin": 0.0,
    "TyresTemperatureAvg": 59.447506252610594,
    "TyresTemperatureMax": 77.250892108337666,
    "TyresTemperatureMin": 44.351899516139383,
    "TyresWearAvg": 97.205726802349091,
    "TyresWearMax": 99.1530179977417,
    "TyresWearMin": 94.076836109161377,
    "TyreTemperatureFrontLeft": 77.250892108337666,
    "TyreTemperatureFrontRight": 70.61520270471442,
    "TyreTemperatureRearLeft": 44.351899516139383,
    "TyreTemperatureRearRight": 45.572030681250908,
    "TyreTemperatureFrontLeftInner": 100.72524896005842,
    "TyreTemperatureFrontLeftMiddle": 83.2607623084225,
    "TyreTemperatureFrontLeftOuter": 47.766665056532133,
    "TyreTemperatureFrontRightInner": 97.318366094712815,
    "TyreTemperatureFrontRightMiddle": 74.6048379899022,
    "TyreTemperatureFrontRightOuter": 39.922404029528195,
    "TyreTemperatureRearLeftInner": 51.949578685750055,
    "TyreTemperatureRearLeftMiddle": 45.208616667571505,
    "TyreTemperatureRearLeftOuter": 35.897503195096476,
    "TyreTemperatureRearRightInner": 52.234531885525428,
    "TyreTemperatureRearRightMiddle": 45.744497810136238,
    "TyreTemperatureRearRightOuter": 38.737062348091058,
    "TyreWearFrontLeft": 94.076836109161377,
    "TyreWearFrontRight": 96.467453241348267,
    "TyreWearRearLeft": 99.12559986114502,
    "TyreWearRearRight": 99.1530179977417,
    "WaterTemperature": 56.405449876007253,
    "TyrePressureUnit": "Kpa",
    "Sector1Time": null,
    "Sector2Time": null,
    "Sector1LastLapTime": null,
    "Sector2LastLapTime": null,
    "Sector3LastLapTime": null,
    "Sector1BestLapTime": null,
    "Sector2BestLapTime": null,
    "Sector3BestLapTime": null,
    "Sector1BestTime": null,
    "Sector2BestTime": null,
    "Sector3BestTime": null,
    "OpponentsCount": 5,
    "CarSettings_MaxRPM": 7300.0,
    "CarSettings_MaxFUEL": 100.0,
    "CarSettings_RedLineRPM": 6205.0,
    "CarSettings_MinimumShownRPM": 0.0,
    "CarSettings_CurrentDisplayedRPMPercent": 87.171814878330849,
    "CarSettings_RPMRedLineReached": 1.0,
    "CarSettings_RedLineDisplayedPercent": 85.0,
    "CarSettings_RPMShiftLight1": 1.0,
    "CarSettings_RPMShiftLight2": 1.0,
    "CarSettings_RPMRedLineSetting": 85.0,
    "PacketTime": "2018-06-21T16:58:39.1730268+02:00",
    "MaxSpeedKmh": 241.71,
    "MaxSpeedMph": 150.19,
    "MaxSpeedLocal": 241.71,
    "CarClass": "ES_GTE",
    "SelfsplitDelta": null,
    "BestSplitDelta": null,
    "BestLapOpponent": {
      "Name": "Johannes van Overbeek",
      "Position": 1,
      "PositionInClass": 1,
      "Coordinates": [
        9.7485599517822266,
        88.4277114868164,
        2078.450927734375
      ],
      "CarName": "16WEC Extreme Speed Motorsports",
      "IsPlayer": false,
      "BestLapTime": "00:01:56.6210000",
      "LastLapTime": "00:01:56.6210000",
      "DeltaToBest": 0.0,
      "DeltaToPlayer": null,
      "CarClass": "ES_P2",
      "IsCarInPit": false,
      "IsCarInPitLane": false,
      "Initials": "JVO",
      "IRacing_IRating": null,
      "CurrentLap": 3,
      "TrackPositionPercent": 0.62027862475407591,
      "TrackPositionPercentToPlayer": 0.107128,
      "CarNumber": "30",
      "CurrentLapHighPrecision": 2.6202786247540759,
      "GaptoLeader": 0.0,
      "GaptoClassLeader": null,
      "GaptoLeaderSimHub": 0.0,
      "LapsToLeader": 0,
      "LapsToClassLeader": -2,
      "LapsToPlayer": 2,
      "GaptoPlayer": null,
      "BestLapSector1": 42.966,
      "BestLapSector2": 39.886,
      "BestLapSector3": 33.769,
      "BestLapSector1Cumulated": 42.966,
      "BestLapSector2Cumulated": 82.852,
      "BestLapSector3Cumulated": 116.621,
      "LastLapSector1": 42.966,
      "LastLapSector2": 39.886,
      "LastLapSector3": 33.769,
      "BestSector1": 42.966,
      "BestSector2": 39.886,
      "BestSector3": 33.769,
      "Speed": 28.540252144947452,
      "RelativeGapToPlayer": -12.493,
      "RelativeDistanceToPlayer": -668.1
    },
    "TrackLength": 6236.44140625,
    "FuelUnit": "Liters"
  },
  "GameRunning": true,
  "GamePath": null,
  "GamePaused": false,
  "GameName": "RFactor2"
}