{
  "NewData": {
    "ABSActive": 0,
    "ABSLevel": 0,
    "AirTemperature": 13.100418395757288,
    "AllTimeBest": "00:00:00",
    "BestLapTime": "00:00:00",
    "Brake": 0.0,
    "BrakeBias": 64.0,
    "BrakesTemperatureAvg": 0.0,
    "BrakesTemperatureMax": 0.0,
    "BrakesTemperatureMin": 0.0,
    "BrakeTemperatureFrontLeft": 474.83151121092988,
    "BrakeTemperatureFrontRight": 480.24897584828705,
    "BrakeTemperatureRearLeft": 301.64330007181491,
    "BrakeTemperatureRearRight": 302.39571060192179,
    "CarCoordinates": [
      -387.74703979492188,
      3.7530555725097656,
      12.826892852783203
    ],
    "Rotation": 0.0,
    "CarDamage1": 0.0,
    "CarDamage2": 0.0,
    "CarDamage3": 0.0,
    "CarDamage4": 0.0,
    "CarDamage5": 0.0,
    "CarDamagesAvg": 0.0,
    "CarDamagesMax": 0.0,
    "CarDamagesMin": 0.0,
    "CarModel": "16WEC Aston Martin Racing",
    "Clutch": 100.0,
    "CompletedLaps": 1,
    "CurrentLap": 2,
    "CurrentLapTime": "00:00:10.4297782",
    "CurrentSectorIndex": 1,
    "DeltaToAllTimeBest": null,
    "DeltaToSessionBest": null,
    "DRSAvailable": 1,
    "DRSEnabled": 0,
    "EngineTorque": -59.75467491839224,
    "FilteredRpms": 4280.9623652590408,
    "FilteredSpeedKmh": 91.35,
    "FilteredSpeedLocal": 91.35,
    "FilteredSpeedMph": 56.76,
    "Flag_Black": 0,
    "Flag_Blue": 0,
    "Flag_Checkered": 0,
    "Flag_Name": "",
    "Flag_White": 0,
    "Flag_Yellow": 0,
    "Fuel": 57.657657623291016,
    "Throttle": 10.7608862221241,
    "Gear": "6",
    "IsInPit": 0,
    "IsInPitLane": 0,
    "LastLapTime": "00:00:00",
    "LastSectorTime": "00:00:00",
    "MapAllowed": true,
    "MaxEngineTorque": 574.50815449082074,
    "MaxFuel": 100.0,
    "MaxRpm": 7300.0,
    "MaxTurbo": 0.0,
    "OilPressure": 0.0,
    "OilTemperature": 73.599722848284273,
    "Opponents": [
      {
        "Name": "Johannes van Overbeek",
        "Position": 1,
        "PositionInClass": 1,
        "Coordinates": [
          -701.70843505859375,
          163.40457153320313,
          1899.1976318359375
        ],
        "CarName": "16WEC Extreme Speed Motorsports",
        "IsPlayer": false,
        "BestLapTime": "00:01:56.6210000",
        "LastLapTime": "00:01:56.7910000",
        "DeltaToBest": 0.0,
        "DeltaToPlayer": null,
        "CarClass": "ES_P2",
        "IsCarInPit": false,
        "IsCarInPitLane": false,
        "Initials": "JVO",
        "IRacing_IRating": null,
        "CurrentLap": 4,
        "TrackPositionPercent": 0.49222559533838722,
        "TrackPositionPercentToPlayer": 0.425287,
        "CarNumber": "30",
        "CurrentLapHighPrecision": 3.4922255953383874,
        "GaptoLeader": 0.0,
        "GaptoClassLeader": null,
        "GaptoLeaderSimHub": 0.0,
        "LapsToLeader": 0,
        "LapsToClassLeader": -2,
        "LapsToPlayer": 2,
        "GaptoPlayer": null,
        "BestLapSector1": 42.966,
        "BestLapSector2": 39.886,
        "BestLapSector3": 33.769,
        "BestLapSector1Cumulated": 42.966,
        "BestLapSector2Cumulated": 82.852,
        "BestLapSector3Cumulated": 116.621,
        "LastLapSector1": 43.278,
        "LastLapSector2": 39.9,
        "LastLapSector3": 33.613,
        "BestSector1": 43.278,
        "BestSector2": 39.9,
        "BestSector3": 33.613,
        "Speed": 67.277950623613023,
        "RelativeGapToPlayer": -49.597,
        "RelativeDistanceToPlayer": -2652.28
      },
      {
        "Name": "Danny Watts",
        "Position": 2,
        "PositionInClass": 2,
        "Coordinates": [
          -594.1585693359375,
          80.27972412109375,
          1083.375
        ],
        "CarName": "16WEC Strakka Racing",
        "IsPlayer": false,
        "BestLapTime": "00:01:56.7950000",
        "LastLapTime": "00:01:58.7120000",
        "DeltaToBest": 0.174,
        "DeltaToPlayer": null,
        "CarClass": "ES_P2",
        "IsCarInPit": false,
        "IsCarInPitLane": false,
        "Initials": "DWA",
        "IRacing_IRating": null,
        "CurrentLap": 4,
        "TrackPositionPercent": 0.27183641434010908,
        "TrackPositionPercentToPlayer": 0.204898,
        "CarNumber": "42",
        "CurrentLapHighPrecision": 3.2718364143401093,
        "GaptoLeader": 28.858631134033203,
        "GaptoClassLeader": null,
        "GaptoLeaderSimHub": 25.702006677200188,
        "LapsToLeader": 0,
        "LapsToClassLeader": -2,
        "LapsToPlayer": 2,
        "GaptoPlayer": null,
        "BestLapSector1": 42.533,
        "BestLapSector2": 40.325,
        "BestLapSector3": 33.937,
        "BestLapSector1Cumulated": 42.533,
        "BestLapSector2Cumulated": 82.858,
        "BestLapSector3Cumulated": 116.795,
        "LastLapSector1": 42.533,
        "LastLapSector2": 41.176,
        "LastLapSector3": 35.002,
        "BestSector1": 42.533,
        "BestSector2": 41.176,
        "BestSector3": 35.002,
        "Speed": 52.655542771146756,
        "RelativeGapToPlayer": -23.895,
        "RelativeDistanceToPlayer": -1277.83
      },
      {
        "Name": "David Heinemeier Hansson",
        "Position": 3,
        "PositionInClass": 1,
        "Coordinates": [
          -397.05126953125,
          37.308448791503906,
          904.5736083984375
        ],
        "CarName": "16WEC Proton Competition",
        "IsPlayer": false,
        "BestLapTime": "00:00:00",
        "LastLapTime": "00:00:00",
        "DeltaToBest": null,
        "DeltaToPlayer": null,
        "CarClass": "ES_GTE",
        "IsCarInPit": false,
        "IsCarInPitLane": false,
        "Initials": "DHH",
        "IRacing_IRating": null,
        "CurrentLap": 2,
        "TrackPositionPercent": 0.21072867295238609,
        "TrackPositionPercentToPlayer": 0.14379,
        "CarNumber": "88",
        "CurrentLapHighPrecision": 1.2107286729523861,
        "GaptoLeader": null,
        "GaptoClassLeader": null,
        "GaptoLeaderSimHub": 266.07045258557787,
        "LapsToLeader": 2,
        "LapsToClassLeader": 0,
        "LapsToPlayer": 0,
        "GaptoPlayer": null,
        "BestLapSector1": null,
        "BestLapSector2": null,
        "BestLapSector3": null,
        "BestLapSector1Cumulated": null,
        "BestLapSector2Cumulated": null,
        "BestLapSector3Cumulated": null,
        "LastLapSector1": null,
        "LastLapSector2": null,
        "LastLapSector3": null,
        "BestSector1": null,
        "BestSector2": null,
        "BestSector3": null,
        "Speed": 67.9174593330586,
        "RelativeGapToPlayer": -16.769,
        "RelativeDistanceToPlayer": -896.74
      },
      {
        "Name": "Filipe Albuquerque",
        "Position": 4,
        "PositionInClass": 3,
        "Coordinates": [
          133.96380615234375,
          9.4200048446655273,
          802.34979248046875
        ],
        "CarName": "16WEC RGR SPort by Morand",
        "IsPlayer": false,
        "BestLapTime": "00:00:00",
        "LastLapTime": "00:00:00",
        "DeltaToBest": null,
        "DeltaToPlayer": null,
        "CarClass": "ES_P2",
        "IsCarInPit": false,
        "IsCarInPitLane": false,
        "Initials": "FAL",
        "IRacing_IRating": null,
        "CurrentLap": 1,
        "TrackPositionPercent": 0.83810785773387142,
        "TrackPositionPercentToPlayer": -0.228831,
        "CarNumber": "43",
        "CurrentLapHighPrecision": 0.83810785773387142,
        "GaptoLeader": null,
        "GaptoClassLeader": null,
        "GaptoLeaderSimHub": 309.52586467717629,
        "LapsToLeader": 2,
        "LapsToClassLeader": 0,
        "LapsToPlayer": 0,
        "GaptoPlayer": null,
        "BestLapSector1": null,
        "BestLapSector2": null,
        "BestLapSector3": null,
        "BestLapSector1Cumulated": null,
        "BestLapSector2Cumulated": null,
        "BestLapSector3Cumulated": null,
        "LastLapSector1": null,
        "LastLapSector2": null,
        "LastLapSector3": null,
        "BestSector1": null,
        "BestSector2": null,
        "BestSector3": null,
        "Speed": 75.230715962658067,
        "RelativeGapToPlayer": 26.687,
        "RelativeDistanceToPlayer": 1427.09
      },
      {
        "Name": "Pieter-Jan Claeysens",
        "Position": 5,
        "PositionInClass": 2,
        "Coordinates": [
          -387.46331787109375,
          3.6102981567382812,
          8.7691659927368164
        ],
        "CarName": "16WEC Aston Martin Racing",
        "IsPlayer": true,
        "BestLapTime": "00:00:00",
        "LastLapTime": "00:00:00",
        "DeltaToBest": null,
        "DeltaToPlayer": null,
        "CarClass": "ES_GTE",
        "IsCarInPit": false,
        "IsCarInPitLane": false,
        "Initials": "PCL",
        "IRacing_IRating": null,
        "CurrentLap": 2,
        "TrackPositionPercent": 0.066938618285355286,
        "TrackPositionPercentToPlayer": null,
        "CarNumber": "98",
        "CurrentLapHighPrecision": 1.0669386182853553,
        "GaptoLeader": null,
        "GaptoClassLeader": null,
        "GaptoLeaderSimHub": 282.83939255090166,
        "LapsToLeader": 2,
        "LapsToClassLeader": 0,
        "LapsToPlayer": 0,
        "GaptoPlayer": null,
        "BestLapSector1": null,
        "BestLapSector2": null,
        "BestLapSector3": null,
        "BestLapSector1Cumulated": null,
        "BestLapSector2Cumulated": null,
        "BestLapSector3Cumulated": null,
        "LastLapSector1": null,
        "LastLapSector2": null,
        "LastLapSector3": null,
        "BestSector1": null,
        "BestSector2": null,
        "BestSector3": null,
        "Speed": 25.506729114329282,
        "RelativeGapToPlayer": null,
        "RelativeDistanceToPlayer": null
      }
    ],
    "PitLimiterOn": 0,
    "Position": 5,
    "RemainingLaps": 0,
    "ReplayMode": "Live",
    "RoadTemperature": 13.100418395757288,
    "Rpms": 4280.9623652590408,
    "SessionTimeLeft": "03:52:05.6380000",
    "SessionTypeName": "Practice",
    "SpeedKmh": 91.35,
    "SpeedLocal": 91.35,
    "SpeedLocalUnit": "KMH",
    "SpeedMph": 56.76,
    "TCActive": 0,
    "TCLevel": 3,
    "TotalLaps": 0,
    "TrackCode": "Bathurst",
    "TrackConfig": null,
    "TrackName": "Bathurst",
    "Turbo": 0.0,
    "TurboPercent": 0.0,
    "TyrePressureFrontLeft": 195.78455402424572,
    "TyrePressureFrontRight": 199.05288566137932,
    "TyrePressureRearLeft": 185.75301546669547,
    "TyrePressureRearRight": 186.94930872916791,
    "TyreDirtFrontLeft": 0.0,
    "TyreDirtFrontRight": 0.0,
    "TyreDirtRearLeft": 0.0,
    "TyreDirtRearRight": 0.0,
    "TyresDirtyLevelAvg": 0.0,
    "TyresDirtyLevelMax": 0.0,
    "TyresDirtyLevelMin": 0.0,
    "TyresTemperatureAvg": 54.563539070904412,
    "TyresTemperatureMax": 60.922615258857718,
    "TyresTemperatureMin": 47.294261856728326,
    "TyresWearAvg": 94.007870554924011,
    "TyresWearMax": 97.524565458297729,
    "TyresWearMin": 91.558229923248291,
    "TyreTemperatureFrontLeft": 47.294261856728326,
    "TyreTemperatureFrontRight": 60.922615258857718,
    "TyreTemperatureRearLeft": 50.151204061783176,
    "TyreTemperatureRearRight": 59.886075106248427,
    "TyreTemperatureFrontLeftInner": 61.461354068270396,
    "TyreTemperatureFrontLeftMiddle": 46.08471419726834,
    "TyreTemperatureFrontLeftOuter": 34.336717304646243,
    "TyreTemperatureFrontRightInner": 64.595315078220949,
    "TyreTemperatureFrontRightMiddle": 60.962151382866466,
    "TyreTemperatureFrontRightOuter": 57.210379315485739,
    "TyreTemperatureRearLeftInner": 60.950848345789382,
    "TyreTemperatureRearLeftMiddle": 50.555990948590818,
    "TyreTemperatureRearLeftOuter": 38.946772890969442,
    "TyreTemperatureRearRightInner": 61.944468891335816,
    "TyreTemperatureRearRightMiddle": 59.803669665310167,
    "TyreTemperatureRearRightOuter": 57.910086762099354,
    "TyreWearFrontLeft": 93.8531756401062,
    "TyreWearFrontRight": 91.558229923248291,
    "TyreWearRearLeft": 97.524565458297729,
    "TyreWearRearRight": 93.095511198043823,
    "WaterTemperature": 62.4966850119111,
    "TyrePressureUnit": "Kpa",
    "Sector1Time": null,
    "Sector2Time": null,
    "Sector1LastLapTime": null,
    "Sector2LastLapTime": null,
    "Sector3LastLapTime": null,
    "Sector1BestLapTime": null,
    "Sector2BestLapTime": null,
    "Sector3BestLapTime": null,
    "Sector1BestTime": null,
    "Sector2BestTime": null,
    "Sector3BestTime": null,
    "OpponentsCount": 5,
    "CarSettings_MaxRPM": 7300.0,
    "CarSettings_MaxFUEL": 100.0,
    "CarSettings_RedLineRPM": 6205.0,
    "CarSettings_MinimumShownRPM": 0.0,
    "CarSettings_CurrentDisplayedRPMPercent": 58.643320072041647,
    "CarSettings_RPMRedLineReached": 0.0,
    "CarSettings_RedLineDisplayedPercent": 85.0,
    "CarSettings_RPMShiftLight1": 0.0,
    "CarSettings_RPMShiftLight2": 0.0,
    "CarSettings_RPMRedLineSetting": 85.0,
    "PacketTime": "2018-06-21T17:00:19.6896662+02:00",
    "MaxSpeedKmh": 271.88,
    "MaxSpeedMph": 168.94,
    "MaxSpeedLocal": 271.88,
    "CarClass": "ES_GTE",
    "SelfsplitDelta": null,
    "BestSplitDelta": null,
    "BestLapOpponent": {
      "Name": "Johannes van Overbeek",
      "Position": 1,
      "PositionInClass": 1,
      "Coordinates": [
        -701.70843505859375,
        163.40457153320313,
        1899.1976318359375
      ],
      "CarName": "16WEC Extreme Speed Motorsports",
      "IsPlayer": false,
      "BestLapTime": "00:01:56.6210000",
      "LastLapTime": "00:01:56.7910000",
      "DeltaToBest": 0.0,
      "DeltaToPlayer": null,
      "CarClass": "ES_P2",
      "IsCarInPit": false,
      "IsCarInPitLane": false,
      "Initials": "JVO",
      "IRacing_IRating": null,
      "CurrentLap": 4,
      "TrackPositionPercent": 0.49222559533838722,
      "TrackPositionPercentToPlayer": 0.425287,
      "CarNumber": "30",
      "CurrentLapHighPrecision": 3.4922255953383874,
      "GaptoLeader": 0.0,
      "GaptoClassLeader": null,
      "GaptoLeaderSimHub": 0.0,
      "LapsToLeader": 0,
      "LapsToClassLeader": -2,
      "LapsToPlayer": 2,
      "GaptoPlayer": null,
      "BestLapSector1": 42.966,
      "BestLapSector2": 39.886,
      "BestLapSector3": 33.769,
      "BestLapSector1Cumulated": 42.966,
      "BestLapSector2Cumulated": 82.852,
      "BestLapSector3Cumulated": 116.621,
      "LastLapSector1": 43.278,
      "LastLapSector2": 39.9,
      "LastLapSector3": 33.613,
      "BestSector1": 43.278,
      "BestSector2": 39.9,
      "BestSector3": 33.613,
      "Speed": 67.277950623613023,
      "RelativeGapToPlayer": -49.597,
      "RelativeDistanceToPlayer": -2652.28
    },
    "TrackLength": 6236.44140625,
    "FuelUnit": "Liters"
  },
  "GameRunning": true,
  "GamePath": null,
  "GamePaused": false,
  "GameName": "RFactor2"
}